{"eta_w2_mults": [0.5, 1.0, 1.5, 2.0], "eta_w3_mults": [0.5, 1.0, 1.5, 2.0], "eta_p_mults": [0.5, 1.0, 1.5], "cases": [{"name": "c_circle_uniform", "dish_kind": "circle", "ingredient_kind": "uniform_noisy", "seed": 1, "k_ingredients": 4, "n_people": 3, "baseline": {"fairness": 1.0, "runtime_s": 0.22261157100001583, "eta_w2_init": 10.0, "eta_w3_init": 10.0, "eta_p_init": 6.0}, "best": {"fairness": 1.0, "eta_w2_init": 5.0, "eta_w3_init": 5.0, "eta_p_init": 3.0}}, {"name": "c_ellipse_pepperoni", "dish_kind": "ellipse", "ingredient_kind": "pepperoni_like", "seed": 2, "k_ingredients": 5, "n_people": 4, "baseline": {"fairness": 0.7627293193147993, "runtime_s": 0.7435806210000919, "eta_w2_init": 10.0, "eta_w3_init": 10.0, "eta_p_init": 6.0}, "best": {"fairness": 0.7658369914753672, "eta_w2_init": 5.0, "eta_w3_init": 20.0, "eta_p_init": 6.0}}, {"name": "c_donut_angular", "dish_kind": "donut", "ingredient_kind": "angular_heterogeneous", "seed": 3, "k_ingredients": 4, "n_people": 4, "baseline": {"fairness": 0.6135345837690871, "runtime_s": 1.0235720169998785, "eta_w2_init": 10.0, "eta_w3_init": 10.0, "eta_p_init": 6.0}, "best": {"fairness": 0.6306866011135558, "eta_w2_init": 5.0, "eta_w3_init": 15.0, "eta_p_init": 3.0}}, {"name": "c_crescent_pepperoni_sparse", "dish_kind": "crescent", "ingredient_kind": "pepperoni_like_sparse", "seed": 4, "k_ingredients": 6, "n_people": 4, "baseline": {"fairness": 0.7576098124850124, "runtime_s": 1.4016953949999333, "eta_w2_init": 10.0, "eta_w3_init": 10.0, "eta_p_init": 6.0}, "best": {"fairness": 0.7658178347027388, "eta_w2_init": 15.0, "eta_w3_init": 15.0, "eta_p_init": 6.0}}, {"name": "c_bridge_stripes", "dish_kind": "bridge", "ingredient_kind": "stripes_and_gradient", "seed": 5, "k_ingredients": 4, "n_people": 3, "baseline": {"fairness": 0.9058878868818283, "runtime_s": 0.744319409000127, "eta_w2_init": 10.0, "eta_w3_init": 10.0, "eta_p_init": 6.0}, "best": {"fairness": 0.909516841173172, "eta_w2_init": 15.0, "eta_w3_init": 20.0, "eta_p_init": 3.0}}, {"name": "c_irregular_angular", "dish_kind": "irregular", "ingredient_kind": "angular_heterogeneous", "seed": 6, "k_ingredients": 5, "n_people": 4, "baseline": {"fairness": 0.7803875311540301, "runtime_s": 1.4667874340002527, "eta_w2_init": 10.0, "eta_w3_init": 10.0, "eta_p_init": 6.0}, "best": {"fairness": 0.7858055896638185, "eta_w2_init": 5.0, "eta_w3_init": 15.0, "eta_p_init": 6.0}}, {"name": "c_circle_pepperoni_sparse", "dish_kind": "circle", "ingredient_kind": "pepperoni_like_sparse", "seed": 7, "k_ingredients": 4, "n_people": 2, "baseline": {"fairness": 0.9060435891151428, "runtime_s": 0.45306020199996055, "eta_w2_init": 10.0, "eta_w3_init": 10.0, "eta_p_init": 6.0}, "best": {"fairness": 0.9064265489578247, "eta_w2_init": 5.0, "eta_w3_init": 10.0, "eta_p_init": 3.0}}, {"name": "c_ellipse_stripes_gradient", "dish_kind": "ellipse", "ingredient_kind": "stripes_and_gradient", "seed": 8, "k_ingredients": 6, "n_people": 3, "baseline": {"fairness": 0.9291684350259426, "runtime_s": 0.2732969599996977, "eta_w2_init": 10.0, "eta_w3_init": 10.0, "eta_p_init": 6.0}, "best": {"fairness": 0.9351741870069715, "eta_w2_init": 5.0, "eta_w3_init": 5.0, "eta_p_init": 6.0}}], "global_cfg_agg": {"5,5,3": {"eta_w2_init": 5.0, "eta_w3_init": 5.0, "eta_p_init": 3.0, "n": 8, "fairness_sum": 6.6213364729827635, "runtime_sum": 7.458841071000279, "fairness_avg": 0.8276670591228454, "runtime_avg_s": 0.9323551338750349}, "5,5,6": {"eta_w2_init": 5.0, "eta_w3_init": 5.0, "eta_p_init": 6.0, "n": 8, "fairness_sum": 6.642050043976763, "runtime_sum": 6.5584507019998455, "fairness_avg": 0.8302562554970954, "runtime_avg_s": 0.8198063377499807}, "5,5,9": {"eta_w2_init": 5.0, "eta_w3_init": 5.0, "eta_p_init": 9.0, "n": 8, "fairness_sum": 6.671486927936453, "runtime_sum": 6.183415879000222, "fairness_avg": 0.8339358659920566, "runtime_avg_s": 0.7729269848750278}, "5,10,3": {"eta_w2_init": 5.0, "eta_w3_init": 10.0, "eta_p_init": 3.0, "n": 8, "fairness_sum": 6.589523292842551, "runtime_sum": 7.796233473999564, "fairness_avg": 0.8236904116053189, "runtime_avg_s": 0.9745291842499455}, "5,10,6": {"eta_w2_init": 5.0, "eta_w3_init": 10.0, "eta_p_init": 6.0, "n": 8, "fairness_sum": 6.655361157745842, "runtime_sum": 6.307659272999899, "fairness_avg": 0.8319201447182303, "runtime_avg_s": 0.7884574091249874}, "5,10,9": {"eta_w2_init": 5.0, "eta_w3_init": 10.0, "eta_p_init": 9.0, "n": 8, "fairness_sum": 6.657751858686704, "runtime_sum": 6.406358393999653, "fairness_avg": 0.832218982335838, "runtime_avg_s": 0.8007947992499567}, "5,15,3": {"eta_w2_init": 5.0, "eta_w3_init": 15.0, "eta_p_init": 3.0, "n": 8, "fairness_sum": 6.617909181874783, "runtime_sum": 6.833275125000455, "fairness_avg": 0.8272386477343479, "runtime_avg_s": 0.8541593906250569}, "5,15,6": {"eta_w2_init": 5.0, "eta_w3_init": 15.0, "eta_p_init": 6.0, "n": 8, "fairness_sum": 6.6681971597611795, "runtime_sum": 6.072996863000299, "fairness_avg": 0.8335246449701474, "runtime_avg_s": 0.7591246078750373}, "5,15,9": {"eta_w2_init": 5.0, "eta_w3_init": 15.0, "eta_p_init": 9.0, "n": 8, "fairness_sum": 6.657377467548022, "runtime_sum": 5.9313339489999635, "fairness_avg": 0.8321721834435027, "runtime_avg_s": 0.7414167436249954}, "5,20,3": {"eta_w2_init": 5.0, "eta_w3_init": 20.0, "eta_p_init": 3.0, "n": 8, "fairness_sum": 6.589349449254923, "runtime_sum": 5.99886387900051, "fairness_avg": 0.8236686811568654, "runtime_avg_s": 0.7498579848750637}, "5,20,6": {"eta_w2_init": 5.0, "eta_w3_init": 20.0, "eta_p_init": 6.0, "n": 8, "fairness_sum": 6.657898462195087, "runtime_sum": 5.925420037999629, "fairness_avg": 0.8322373077743859, "runtime_avg_s": 0.7406775047499536}, "5,20,9": {"eta_w2_init": 5.0, "eta_w3_init": 20.0, "eta_p_init": 9.0, "n": 8, "fairness_sum": 6.664737752428812, "runtime_sum": 5.828542954999648, "fairness_avg": 0.8330922190536015, "runtime_avg_s": 0.728567869374956}, "10,5,3": {"eta_w2_init": 10.0, "eta_w3_init": 5.0, "eta_p_init": 3.0, "n": 8, "fairness_sum": 6.632774947793041, "runtime_sum": 6.690388479000376, "fairness_avg": 0.8290968684741301, "runtime_avg_s": 0.836298559875047}, "10,5,6": {"eta_w2_init": 10.0, "eta_w3_init": 5.0, "eta_p_init": 6.0, "n": 8, "fairness_sum": 6.642050043976763, "runtime_sum": 5.609541160999925, "fairness_avg": 0.8302562554970954, "runtime_avg_s": 0.7011926451249906}, "10,5,9": {"eta_w2_init": 10.0, "eta_w3_init": 5.0, "eta_p_init": 9.0, "n": 8, "fairness_sum": 6.674067152442753, "runtime_sum": 6.443584360999921, "fairness_avg": 0.8342583940553441, "runtime_avg_s": 0.8054480451249901}, "10,10,3": {"eta_w2_init": 10.0, "eta_w3_init": 10.0, "eta_p_init": 3.0, "n": 8, "fairness_sum": 6.589523292842551, "runtime_sum": 5.896733970999321, "fairness_avg": 0.8236904116053189, "runtime_avg_s": 0.7370917463749151}, "10,10,6": {"eta_w2_init": 10.0, "eta_w3_init": 10.0, "eta_p_init": 6.0, "n": 8, "fairness_sum": 6.655361157745842, "runtime_sum": 6.143838894000055, "fairness_avg": 0.8319201447182303, "runtime_avg_s": 0.7679798617500069}, "10,10,9": {"eta_w2_init": 10.0, "eta_w3_init": 10.0, "eta_p_init": 9.0, "n": 8, "fairness_sum": 6.657751858686704, "runtime_sum": 6.378233407999687, "fairness_avg": 0.832218982335838, "runtime_avg_s": 0.7972791759999609}, "10,15,3": {"eta_w2_init": 10.0, "eta_w3_init": 15.0, "eta_p_init": 3.0, "n": 8, "fairness_sum": 6.6193954550524685, "runtime_sum": 6.376941408000221, "fairness_avg": 0.8274244318815586, "runtime_avg_s": 0.7971176760000276}, "10,15,6": {"eta_w2_init": 10.0, "eta_w3_init": 15.0, "eta_p_init": 6.0, "n": 8, "fairness_sum": 6.6681971597611795, "runtime_sum": 5.9219988129998455, "fairness_avg": 0.8335246449701474, "runtime_avg_s": 0.7402498516249807}, "10,15,9": {"eta_w2_init": 10.0, "eta_w3_init": 15.0, "eta_p_init": 9.0, "n": 8, "fairness_sum": 6.657377467548022, "runtime_sum": 6.242548693000117, "fairness_avg": 0.8321721834435027, "runtime_avg_s": 0.7803185866250146}, "10,20,3": {"eta_w2_init": 10.0, "eta_w3_init": 20.0, "eta_p_init": 3.0, "n": 8, "fairness_sum": 6.5879217670248185, "runtime_sum": 6.759619138000289, "fairness_avg": 0.8234902208781023, "runtime_avg_s": 0.8449523922500362}, "10,20,6": {"eta_w2_init": 10.0, "eta_w3_init": 20.0, "eta_p_init": 6.0, "n": 8, "fairness_sum": 6.657898462195087, "runtime_sum": 6.479833371999121, "fairness_avg": 0.8322373077743859, "runtime_avg_s": 0.8099791714998901}, "10,20,9": {"eta_w2_init": 10.0, "eta_w3_init": 20.0, "eta_p_init": 9.0, "n": 8, "fairness_sum": 6.664737752428812, "runtime_sum": 6.015269757999704, "fairness_avg": 0.8330922190536015, "runtime_avg_s": 0.751908719749963}, "15,5,3": {"eta_w2_init": 15.0, "eta_w3_init": 5.0, "eta_p_init": 3.0, "n": 8, "fairness_sum": 6.619984098912749, "runtime_sum": 7.399212085000272, "fairness_avg": 0.8274980123640936, "runtime_avg_s": 0.924901510625034}, "15,5,6": {"eta_w2_init": 15.0, "eta_w3_init": 5.0, "eta_p_init": 6.0, "n": 8, "fairness_sum": 6.641795606649378, "runtime_sum": 5.775810170000113, "fairness_avg": 0.8302244508311722, "runtime_avg_s": 0.7219762712500142}, "15,5,9": {"eta_w2_init": 15.0, "eta_w3_init": 5.0, "eta_p_init": 9.0, "n": 8, "fairness_sum": 6.674067152442753, "runtime_sum": 6.025432967999677, "fairness_avg": 0.8342583940553441, "runtime_avg_s": 0.7531791209999597}, "15,10,3": {"eta_w2_init": 15.0, "eta_w3_init": 10.0, "eta_p_init": 3.0, "n": 8, "fairness_sum": 6.589523292842551, "runtime_sum": 6.596133173000453, "fairness_avg": 0.8236904116053189, "runtime_avg_s": 0.8245166466250566}, "15,10,6": {"eta_w2_init": 15.0, "eta_w3_init": 10.0, "eta_p_init": 6.0, "n": 8, "fairness_sum": 6.655717787236695, "runtime_sum": 6.136677226999382, "fairness_avg": 0.8319647234045868, "runtime_avg_s": 0.7670846533749227}, "15,10,9": {"eta_w2_init": 15.0, "eta_w3_init": 10.0, "eta_p_init": 9.0, "n": 8, "fairness_sum": 6.657751858686704, "runtime_sum": 5.840918322000107, "fairness_avg": 0.832218982335838, "runtime_avg_s": 0.7301147902500134}, "15,15,3": {"eta_w2_init": 15.0, "eta_w3_init": 15.0, "eta_p_init": 3.0, "n": 8, "fairness_sum": 6.617909181874783, "runtime_sum": 6.251928499000769, "fairness_avg": 0.8272386477343479, "runtime_avg_s": 0.7814910623750961}, "15,15,6": {"eta_w2_init": 15.0, "eta_w3_init": 15.0, "eta_p_init": 6.0, "n": 8, "fairness_sum": 6.6769242254283405, "runtime_sum": 5.698276459999761, "fairness_avg": 0.8346155281785426, "runtime_avg_s": 0.7122845574999701}, "15,15,9": {"eta_w2_init": 15.0, "eta_w3_init": 15.0, "eta_p_init": 9.0, "n": 8, "fairness_sum": 6.656162769522796, "runtime_sum": 6.017607389000659, "fairness_avg": 0.8320203461903495, "runtime_avg_s": 0.7522009236250824}, "15,20,3": {"eta_w2_init": 15.0, "eta_w3_init": 20.0, "eta_p_init": 3.0, "n": 8, "fairness_sum": 6.59687273064119, "runtime_sum": 6.895698784999695, "fairness_avg": 0.8246090913301487, "runtime_avg_s": 0.8619623481249619}, "15,20,6": {"eta_w2_init": 15.0, "eta_w3_init": 20.0, "eta_p_init": 6.0, "n": 8, "fairness_sum": 6.6697916402979445, "runtime_sum": 6.844975035999596, "fairness_avg": 0.8337239550372431, "runtime_avg_s": 0.8556218794999495}, "15,20,9": {"eta_w2_init": 15.0, "eta_w3_init": 20.0, "eta_p_init": 9.0, "n": 8, "fairness_sum": 6.666103278909884, "runtime_sum": 6.427917239999715, "fairness_avg": 0.8332629098637355, "runtime_avg_s": 0.8034896549999644}, "20,5,3": {"eta_w2_init": 20.0, "eta_w3_init": 5.0, "eta_p_init": 3.0, "n": 8, "fairness_sum": 6.619984098912749, "runtime_sum": 6.845944608999616, "fairness_avg": 0.8274980123640936, "runtime_avg_s": 0.855743076124952}, "20,5,6": {"eta_w2_init": 20.0, "eta_w3_init": 5.0, "eta_p_init": 6.0, "n": 8, "fairness_sum": 6.645241474096841, "runtime_sum": 5.480489349000436, "fairness_avg": 0.8306551842621052, "runtime_avg_s": 0.6850611686250545}, "20,5,9": {"eta_w2_init": 20.0, "eta_w3_init": 5.0, "eta_p_init": 9.0, "n": 8, "fairness_sum": 6.674067152442753, "runtime_sum": 6.481836948999899, "fairness_avg": 0.8342583940553441, "runtime_avg_s": 0.8102296186249873}, "20,10,3": {"eta_w2_init": 20.0, "eta_w3_init": 10.0, "eta_p_init": 3.0, "n": 8, "fairness_sum": 6.589523292842551, "runtime_sum": 6.592324591000306, "fairness_avg": 0.8236904116053189, "runtime_avg_s": 0.8240405738750383}, "20,10,6": {"eta_w2_init": 20.0, "eta_w3_init": 10.0, "eta_p_init": 6.0, "n": 8, "fairness_sum": 6.657053899855141, "runtime_sum": 6.546885226000086, "fairness_avg": 0.8321317374818926, "runtime_avg_s": 0.8183606532500107}, "20,10,9": {"eta_w2_init": 20.0, "eta_w3_init": 10.0, "eta_p_init": 9.0, "n": 8, "fairness_sum": 6.657751858686704, "runtime_sum": 6.54441282300013, "fairness_avg": 0.832218982335838, "runtime_avg_s": 0.8180516028750162}, "20,15,3": {"eta_w2_init": 20.0, "eta_w3_init": 15.0, "eta_p_init": 3.0, "n": 8, "fairness_sum": 6.6193954550524685, "runtime_sum": 6.250984672999493, "fairness_avg": 0.8274244318815586, "runtime_avg_s": 0.7813730841249367}, "20,15,6": {"eta_w2_init": 20.0, "eta_w3_init": 15.0, "eta_p_init": 6.0, "n": 8, "fairness_sum": 6.667942826500937, "runtime_sum": 5.538527190000423, "fairness_avg": 0.8334928533126171, "runtime_avg_s": 0.6923158987500528}, "20,15,9": {"eta_w2_init": 20.0, "eta_w3_init": 15.0, "eta_p_init": 9.0, "n": 8, "fairness_sum": 6.656162769522796, "runtime_sum": 5.806194585999492, "fairness_avg": 0.8320203461903495, "runtime_avg_s": 0.7257743232499365}, "20,20,3": {"eta_w2_init": 20.0, "eta_w3_init": 20.0, "eta_p_init": 3.0, "n": 8, "fairness_sum": 6.59687273064119, "runtime_sum": 6.4219333930000175, "fairness_avg": 0.8246090913301487, "runtime_avg_s": 0.8027416741250022}, "20,20,6": {"eta_w2_init": 20.0, "eta_w3_init": 20.0, "eta_p_init": 6.0, "n": 8, "fairness_sum": 6.663341299651002, "runtime_sum": 6.22268314799976, "fairness_avg": 0.8329176624563752, "runtime_avg_s": 0.77783539349997}, "20,20,9": {"eta_w2_init": 20.0, "eta_w3_init": 20.0, "eta_p_init": 9.0, "n": 8, "fairness_sum": 6.666103278909884, "runtime_sum": 6.147577339999771, "fairness_avg": 0.8332629098637355, "runtime_avg_s": 0.7684471674999713}}, "top_configs": [{"eta_w2_init": 15.0, "eta_w3_init": 15.0, "eta_p_init": 6.0, "n": 8, "fairness_sum": 6.6769242254283405, "runtime_sum": 5.698276459999761, "fairness_avg": 0.8346155281785426, "runtime_avg_s": 0.7122845574999701}, {"eta_w2_init": 15.0, "eta_w3_init": 5.0, "eta_p_init": 9.0, "n": 8, "fairness_sum": 6.674067152442753, "runtime_sum": 6.025432967999677, "fairness_avg": 0.8342583940553441, "runtime_avg_s": 0.7531791209999597}, {"eta_w2_init": 10.0, "eta_w3_init": 5.0, "eta_p_init": 9.0, "n": 8, "fairness_sum": 6.674067152442753, "runtime_sum": 6.443584360999921, "fairness_avg": 0.8342583940553441, "runtime_avg_s": 0.8054480451249901}, {"eta_w2_init": 20.0, "eta_w3_init": 5.0, "eta_p_init": 9.0, "n": 8, "fairness_sum": 6.674067152442753, "runtime_sum": 6.481836948999899, "fairness_avg": 0.8342583940553441, "runtime_avg_s": 0.8102296186249873}, {"eta_w2_init": 5.0, "eta_w3_init": 5.0, "eta_p_init": 9.0, "n": 8, "fairness_sum": 6.671486927936453, "runtime_sum": 6.183415879000222, "fairness_avg": 0.8339358659920566, "runtime_avg_s": 0.7729269848750278}, {"eta_w2_init": 15.0, "eta_w3_init": 20.0, "eta_p_init": 6.0, "n": 8, "fairness_sum": 6.6697916402979445, "runtime_sum": 6.844975035999596, "fairness_avg": 0.8337239550372431, "runtime_avg_s": 0.8556218794999495}, {"eta_w2_init": 10.0, "eta_w3_init": 15.0, "eta_p_init": 6.0, "n": 8, "fairness_sum": 6.6681971597611795, "runtime_sum": 5.9219988129998455, "fairness_avg": 0.8335246449701474, "runtime_avg_s": 0.7402498516249807}, {"eta_w2_init": 5.0, "eta_w3_init": 15.0, "eta_p_init": 6.0, "n": 8, "fairness_sum": 6.6681971597611795, "runtime_sum": 6.072996863000299, "fairness_avg": 0.8335246449701474, "runtime_avg_s": 0.7591246078750373}, {"eta_w2_init": 20.0, "eta_w3_init": 15.0, "eta_p_init": 6.0, "n": 8, "fairness_sum": 6.667942826500937, "runtime_sum": 5.538527190000423, "fairness_avg": 0.8334928533126171, "runtime_avg_s": 0.6923158987500528}, {"eta_w2_init": 20.0, "eta_w3_init": 20.0, "eta_p_init": 9.0, "n": 8, "fairness_sum": 6.666103278909884, "runtime_sum": 6.147577339999771, "fairness_avg": 0.8332629098637355, "runtime_avg_s": 0.7684471674999713}], "summary": {"avg_baseline_fairness": 0.8319201447182303, "avg_best_fairness": 0.8374080742616812, "best_overall_fairness": 1.0, "n_cases": 8}}